zylib/__init__.py
zylib/strs.py
zylib-0.0.2.dist-info/LICENSE
zylib-0.0.2.dist-info/METADATA
zylib-0.0.2.dist-info/WHEEL
zylib-0.0.2.dist-info/top_level.txt
zylib-0.0.2.dist-info/RECORD
