Metadata-Version: 2.1
Name: zylib
Version: 0.0.2
Summary: A personal util lib
Home-page: https://github.com/raindrean/zylib
Author: Daniel Yang
Author-email: danielyang004@gmail.com
License: UNKNOWN
Platform: UNKNOWN
Classifier: Programming Language :: Python :: 3
Classifier: License :: OSI Approved :: MIT License
Classifier: Operating System :: OS Independent
Requires-Python: >=3.6
License-File: LICENSE
